{
  "endpointAddress" : "https://when-to-work-backend.onwavemaker.com/api/scheduling/employees",
  "method" : "GET",
  "headers" : {
    "ngrok-skip-browser-warning" : [ "true" ]
  },
  "redirectEnabled" : true,
  "requestBody" : "",
  "queryParams" : {
    "companyId" : "1",
    "endDate" : "2026-03-30",
    "startDate" : "2026-03-23"
  },
  "authDetails" : null,
  "contentType" : "application/json",
  "multiParamInfoList" : [ ],
  "urlBasePath" : "/api",
  "sampleHttpResponseDetails" : {
    "statusCode" : 200,
    "headers" : {
      "Date" : [ "Tue, 31 Mar 2026 11:06:44 GMT" ],
      "Content-Type" : [ "application/json" ],
      "Transfer-Encoding" : [ "chunked" ],
      "Connection" : [ "keep-alive" ]
    },
    "responseBody" : "[{\"employeeId\":1,\"firstName\":\"Carol\",\"lastName\":\"Jones\",\"phones\":[\"555-9922\",\"555-7298\",\"555-3467\",\"555-5369\",\"555-4464\",\"555-0333\",\"555-7236\",\"555-8547\",\"555-5505\",\"555-5123\",\"555-2940\",\"555-8402\",\"555-4931\",\"555-1747\",\"555-1625\",\"555-1588\",\"555-7733\",\"555-1485\",\"555-0256\",\"555-8380\",\"555-1650\",\"555-7481\",\"555-0926\",\"555-4186\",\"555-2523\",\"555-8113\",\"555-5746\",\"555-9141\",\"555-6491\",\"555-7228\",\"555-0478\",\"555-2391\",\"555-4503\",\"555-8850\",\"555-4677\",\"555-9256\",\"555-3303\",\"555-4763\",\"555-3236\",\"555-3619\",\"555-3253\",\"555-0703\",\"555-1093\",\"555-3327\",\"555-9133\",\"555-8230\",\"555-0826\",\"555-9023\",\"555-6417\",\"555-4275\",\"555-1290\",\"555-1483\",\"555-4770\",\"555-4609\",\"555-3357\",\"555-0138\",\"555-8453\",\"555-8224\",\"555-5115\",\"555-2032\",\"555-0642\",\"555-5363\",\"555-0099\",\"555-0244\",\"555-9284\",\"555-1069\",\"555-5698\",\"555-0259\",\"555-6078\",\"555-4804\",\"555-4229\",\"555-3751\",\"555-8732\",\"555-8386\",\"555-1503\",\"555-4972\",\"555-0796\",\"555-5164\",\"555-9159\",\"555-5979\",\"555-7818\",\"555-2155\",\"555-1410\",\"555-8299\",\"555-1690\",\"555-9613\",\"555-9084\",\"555-4257\",\"555-5067\",\"555-8301\",\"555-3075\",\"555-6788\",\"555-8988\",\"555-2254\",\"555-1396\",\"555-7228\",\"555-3286\",\"555-0995\",\"555-3379\",\"555-8671\"],\"availablePositions\":[{\"id\":3,\"name\":\"Bellhop\"}],\"shiftCount\":3,\"totalHours\":24,\"weeklyShifts\":{\"0\":{\"date\":\"2026-03-23\",\"shifts\":[{\"startTime\":\"8:00AM\",\"endTime\":\"4:00PM\",\"position\":\"Server\",\"category\":\"On-Call\",\"description\":\"Generated Shift 309\",\"duration\":8}]},\"1\":{\"date\":\"2026-03-24\",\"shifts\":[{\"startTime\":\"8:00AM\",\"endTime\":\"4:00PM\",\"position\":\"Host\",\"category\":\"Weekend Shift\",\"description\":\"Generated Shift 323\",\"duration\":8}]},\"2\":{\"date\":\"2026-03-25\",\"shifts\":[{\"startTime\":\"8:00AM\",\"endTime\":\"4:00PM\",\"position\":\"Mixologist\",\"category\":\"Night Shift\",\"description\":\"Generated Shift 335\",\"duration\":8}]},\"3\":{\"date\":\"2026-03-26\",\"shifts\":[{\"startTime\":\"10:00PM\",\"endTime\":\"12:00AM\",\"position\":\"Host\",\"category\":\"Night Shift\",\"description\":\"Generated Shift 345\",\"duration\":2}]},\"4\":{\"date\":\"2026-03-27\",\"shifts\":[{\"startTime\":\"12:00AM\",\"endTime\":\"6:00AM\",\"position\":\"Host\",\"category\":\"Night Shift\",\"description\":\"Generated Shift 345\",\"duration\":6}]},\"5\":{\"date\":\"2026-03-28\",\"shifts\":[{\"startTime\":\"8:00AM\",\"endTime\":\"4:00PM\",\"position\":\"Bellhop\",\"category\":\"Night Shift\",\"description\":\"Generated Shift 370\",\"duration\":8}]},\"6\":{\"date\":\"2026-03-29\",\"shifts\":[{\"startTime\":\"8:00AM\",\"endTime\":\"4:00PM\",\"position\":\"Valet\",\"category\":\"Emergency\",\"description\":\"Generated Shift 384\",\"duration\":8}]},\"7\":{\"date\":\"2026-03-30\",\"shifts\":[{\"startTime\":\"8:00AM\",\"endTime\":\"4:00PM\",\"position\":\"Chef\",\"category\":\"Morning Shift\",\"description\":\"Generated Shift 398\",\"duration\":8}]}}}]",
    "convertedResponse" : null
  }
}
