{
  "id" : "f11f6e60-818c-43cd-b925-09dac53e91c7",
  "mergeRequestDetails" : {
    "mergeableRef" : "refs/remotes/origin/main",
    "mergeCommitMessage" : "Merge branch [main]",
    "description" : "Merging branch[main]",
    "type" : "BRANCH_MERGE",
    "fastForwardEnabled" : false,
    "finishMergeOnNoConflicts" : false,
    "pushToVCSOnChanges" : true,
    "rememberApplyOursPathsEnabled" : false,
    "rememberedApplyOursPaths" : null,
    "attributes" : { }
  },
  "commitIdMap" : {
    "PRE_MIGRATED_COMMON_ANCESTOR" : "07c29114a1e178e8c97918bf024dedc85ba7cfe7",
    "COMMON_ANCESTOR" : "4257f73e8b9eaae8415798a6cb2c8ca3e8bd6304",
    "OURS" : "44f8ff17eff341d62e52c82d7a5f3c9e3107018d",
    "PRE_MIGRATED_THEIRS" : "aa2a5d0cafa612e811f9a750b34bd53b7aa1ddd9",
    "THEIRS" : "50bfc04aefee9d350461ad9f46e05800f468a190",
    "INITIAL_MERGE" : "65c39fdd5aeb1da6267e594dd42a657134b231e2",
    "LAST_SYNCED_MERGE" : "65c39fdd5aeb1da6267e594dd42a657134b231e2"
  },
  "conflictedPaths" : [ ],
  "initialContentConflictedPaths" : [ ],
  "initialPathConflictedPaths" : [ ],
  "autoResolvedPaths" : { },
  "pathMergeStatusMap" : {
    "Prefabs" : {
      "path" : "Prefabs",
      "pathType" : "DIR",
      "virtual" : true,
      "branchOutType" : "MODIFIED_IN_THEIRS",
      "branchInType" : "APPLIED_THEIRS",
      "latestBranchInType" : "APPLIED_THEIRS",
      "objectIdsMap" : {
        "COMMON_ANCESTOR" : "10858680e8496f3c3d28eedd7911871164cdb549",
        "OURS" : "10858680e8496f3c3d28eedd7911871164cdb549",
        "THEIRS" : "8594981360f944cf03b93fa1ed048c6d43a28376",
        "INITIAL_MERGE" : "8594981360f944cf03b93fa1ed048c6d43a28376",
        "LAST_SYNCED_MERGE" : "8594981360f944cf03b93fa1ed048c6d43a28376"
      },
      "component" : "PREFAB",
      "conflictedFileParts" : null,
      "conflictsCount" : 0,
      "initialConflictsCount" : 0,
      "description" : null,
      "mergeActionType" : "DEFAULT"
    },
    "Prefabs/Weekview" : {
      "path" : "Prefabs/Weekview",
      "pathType" : "DIR",
      "virtual" : true,
      "branchOutType" : "MODIFIED_IN_THEIRS",
      "branchInType" : "APPLIED_THEIRS",
      "latestBranchInType" : "APPLIED_THEIRS",
      "objectIdsMap" : {
        "COMMON_ANCESTOR" : "0c1d496a49ca37c31a01ae5620bf43c1188710b3",
        "OURS" : "0c1d496a49ca37c31a01ae5620bf43c1188710b3",
        "THEIRS" : "645783601f45d43a040bce82f96a30a186a664bf",
        "INITIAL_MERGE" : "645783601f45d43a040bce82f96a30a186a664bf",
        "LAST_SYNCED_MERGE" : "645783601f45d43a040bce82f96a30a186a664bf"
      },
      "component" : "PREFAB",
      "conflictedFileParts" : null,
      "conflictsCount" : 0,
      "initialConflictsCount" : 0,
      "description" : null,
      "mergeActionType" : "EXPLICIT_MERGE_ONLY"
    },
    "Prefabs/Weekview/Artifact" : {
      "path" : "Prefabs/Weekview/Artifact",
      "pathType" : "FILE",
      "virtual" : true,
      "branchOutType" : "MODIFIED_IN_THEIRS",
      "branchInType" : "APPLIED_THEIRS",
      "latestBranchInType" : "APPLIED_THEIRS",
      "objectIdsMap" : {
        "COMMON_ANCESTOR" : "0ffb49653a4ed927c4ae5e13eeabc508fbb372f3",
        "OURS" : "0ffb49653a4ed927c4ae5e13eeabc508fbb372f3",
        "THEIRS" : "de2d8360c1be7c6308d4a25fc5a5e09a1c237fa2",
        "INITIAL_MERGE" : "de2d8360c1be7c6308d4a25fc5a5e09a1c237fa2",
        "LAST_SYNCED_MERGE" : "de2d8360c1be7c6308d4a25fc5a5e09a1c237fa2"
      },
      "component" : "PREFAB",
      "conflictedFileParts" : null,
      "conflictsCount" : 0,
      "initialConflictsCount" : 0,
      "description" : "Modified in ${THEIRS} from 0.0.7(Published by tcp) to 0.0.8(Published by tcp).In ${OURS} and ${THEIRS}, the Prefab is directly consumed in the project and has no transitive dependencies.",
      "mergeActionType" : "DISABLE_CONTENT_MERGING"
    },
    "Prefabs/WorkPreference" : {
      "path" : "Prefabs/WorkPreference",
      "pathType" : "DIR",
      "virtual" : true,
      "branchOutType" : "NO_CHANGES",
      "branchInType" : "APPLIED_SAME",
      "latestBranchInType" : "APPLIED_SAME",
      "objectIdsMap" : {
        "COMMON_ANCESTOR" : "7dcd89cbe63689ab5005cea9674187e57a825333",
        "OURS" : "7dcd89cbe63689ab5005cea9674187e57a825333",
        "THEIRS" : "7dcd89cbe63689ab5005cea9674187e57a825333",
        "INITIAL_MERGE" : "7dcd89cbe63689ab5005cea9674187e57a825333",
        "LAST_SYNCED_MERGE" : "7dcd89cbe63689ab5005cea9674187e57a825333"
      },
      "component" : "PREFAB",
      "conflictedFileParts" : null,
      "conflictsCount" : 0,
      "initialConflictsCount" : 0,
      "description" : null,
      "mergeActionType" : "EXPLICIT_MERGE_ONLY"
    },
    "Prefabs/WorkPreference/Artifact" : {
      "path" : "Prefabs/WorkPreference/Artifact",
      "pathType" : "FILE",
      "virtual" : true,
      "branchOutType" : "NO_CHANGES",
      "branchInType" : "APPLIED_SAME",
      "latestBranchInType" : "APPLIED_SAME",
      "objectIdsMap" : {
        "COMMON_ANCESTOR" : "f5f7ef6288ddfa7865dbae9d9e905f67528b0fa8",
        "OURS" : "f5f7ef6288ddfa7865dbae9d9e905f67528b0fa8",
        "THEIRS" : "f5f7ef6288ddfa7865dbae9d9e905f67528b0fa8",
        "INITIAL_MERGE" : "f5f7ef6288ddfa7865dbae9d9e905f67528b0fa8",
        "LAST_SYNCED_MERGE" : "f5f7ef6288ddfa7865dbae9d9e905f67528b0fa8"
      },
      "component" : "PREFAB",
      "conflictedFileParts" : null,
      "conflictsCount" : 0,
      "initialConflictsCount" : 0,
      "description" : "In ${OURS} and ${THEIRS}, the Prefab is directly consumed in the project and has no transitive dependencies.",
      "mergeActionType" : "DISABLE_CONTENT_MERGING"
    },
    "Profile Properties" : {
      "path" : "Profile Properties",
      "pathType" : "DIR",
      "virtual" : true,
      "branchOutType" : "NO_CHANGES",
      "branchInType" : "APPLIED_SAME",
      "latestBranchInType" : "APPLIED_SAME",
      "objectIdsMap" : {
        "COMMON_ANCESTOR" : "4762d28af399021efbcc072d18f21efdb4e7a792",
        "OURS" : "4762d28af399021efbcc072d18f21efdb4e7a792",
        "THEIRS" : "4762d28af399021efbcc072d18f21efdb4e7a792",
        "INITIAL_MERGE" : "4762d28af399021efbcc072d18f21efdb4e7a792",
        "LAST_SYNCED_MERGE" : "4762d28af399021efbcc072d18f21efdb4e7a792"
      },
      "component" : "PROFILE",
      "conflictedFileParts" : null,
      "conflictsCount" : 0,
      "initialConflictsCount" : 0,
      "description" : null,
      "mergeActionType" : "EXPLICIT_MERGE_ONLY"
    },
    "Themes" : {
      "path" : "Themes",
      "pathType" : "DIR",
      "virtual" : true,
      "branchOutType" : "NO_CHANGES",
      "branchInType" : "APPLIED_SAME",
      "latestBranchInType" : "APPLIED_SAME",
      "objectIdsMap" : {
        "COMMON_ANCESTOR" : "4e1e0c99b5344b3517b11f5185ea2761c302e28f",
        "OURS" : "4e1e0c99b5344b3517b11f5185ea2761c302e28f",
        "THEIRS" : "4e1e0c99b5344b3517b11f5185ea2761c302e28f",
        "INITIAL_MERGE" : "4e1e0c99b5344b3517b11f5185ea2761c302e28f",
        "LAST_SYNCED_MERGE" : "4e1e0c99b5344b3517b11f5185ea2761c302e28f"
      },
      "component" : "THEME",
      "conflictedFileParts" : null,
      "conflictsCount" : 0,
      "initialConflictsCount" : 0,
      "description" : null,
      "mergeActionType" : "DEFAULT"
    },
    "src" : {
      "path" : "src",
      "pathType" : "DIR",
      "virtual" : false,
      "branchOutType" : "MODIFIED_IN_THEIRS",
      "branchInType" : "APPLIED_THEIRS",
      "latestBranchInType" : "APPLIED_THEIRS",
      "objectIdsMap" : {
        "COMMON_ANCESTOR" : "878fd56abdfbcf6ccf76ae189bbce4bdddc47f00",
        "OURS" : "878fd56abdfbcf6ccf76ae189bbce4bdddc47f00",
        "THEIRS" : "d59bcf01587266399d83ca2e523d9194796d9521",
        "INITIAL_MERGE" : "d59bcf01587266399d83ca2e523d9194796d9521",
        "LAST_SYNCED_MERGE" : "d59bcf01587266399d83ca2e523d9194796d9521"
      },
      "component" : "OTHER",
      "conflictedFileParts" : null,
      "conflictsCount" : 0,
      "initialConflictsCount" : 0,
      "description" : null,
      "mergeActionType" : "DEFAULT"
    },
    "src/main" : {
      "path" : "src/main",
      "pathType" : "DIR",
      "virtual" : false,
      "branchOutType" : "MODIFIED_IN_THEIRS",
      "branchInType" : "APPLIED_THEIRS",
      "latestBranchInType" : "APPLIED_THEIRS",
      "objectIdsMap" : {
        "COMMON_ANCESTOR" : "7687c0d22367269746b5b92a0d6db0f7c8c41b7d",
        "OURS" : "7687c0d22367269746b5b92a0d6db0f7c8c41b7d",
        "THEIRS" : "c82247ff3b467dbc5923e69351adffe237be8637",
        "INITIAL_MERGE" : "c82247ff3b467dbc5923e69351adffe237be8637",
        "LAST_SYNCED_MERGE" : "c82247ff3b467dbc5923e69351adffe237be8637"
      },
      "component" : "OTHER",
      "conflictedFileParts" : null,
      "conflictsCount" : 0,
      "initialConflictsCount" : 0,
      "description" : null,
      "mergeActionType" : "DEFAULT"
    },
    "src/main/webapp" : {
      "path" : "src/main/webapp",
      "pathType" : "DIR",
      "virtual" : false,
      "branchOutType" : "MODIFIED_IN_THEIRS",
      "branchInType" : "APPLIED_THEIRS",
      "latestBranchInType" : "APPLIED_THEIRS",
      "objectIdsMap" : {
        "COMMON_ANCESTOR" : "a7795b6229728be5ba4e60ecba8e8f27ad2c9ea4",
        "OURS" : "a7795b6229728be5ba4e60ecba8e8f27ad2c9ea4",
        "THEIRS" : "e5421e07eaadc251d295ff8e00e13729bbf51515",
        "INITIAL_MERGE" : "e5421e07eaadc251d295ff8e00e13729bbf51515",
        "LAST_SYNCED_MERGE" : "e5421e07eaadc251d295ff8e00e13729bbf51515"
      },
      "component" : "OTHER",
      "conflictedFileParts" : null,
      "conflictsCount" : 0,
      "initialConflictsCount" : 0,
      "description" : null,
      "mergeActionType" : "DEFAULT"
    },
    "src/main/webapp/WEB-INF" : {
      "path" : "src/main/webapp/WEB-INF",
      "pathType" : "DIR",
      "virtual" : false,
      "branchOutType" : "MODIFIED_IN_THEIRS",
      "branchInType" : "APPLIED_THEIRS",
      "latestBranchInType" : "APPLIED_THEIRS",
      "objectIdsMap" : {
        "COMMON_ANCESTOR" : "f51499063859675de9a65e62d215efaf1b87d454",
        "OURS" : "f51499063859675de9a65e62d215efaf1b87d454",
        "THEIRS" : "d29d68d9f2b48c98e44a1cf94a996a6cd2aecca0",
        "INITIAL_MERGE" : "d29d68d9f2b48c98e44a1cf94a996a6cd2aecca0",
        "LAST_SYNCED_MERGE" : "d29d68d9f2b48c98e44a1cf94a996a6cd2aecca0"
      },
      "component" : "OTHER",
      "conflictedFileParts" : null,
      "conflictsCount" : 0,
      "initialConflictsCount" : 0,
      "description" : null,
      "mergeActionType" : "DEFAULT"
    },
    "src/main/webapp/app.css" : {
      "path" : "src/main/webapp/app.css",
      "pathType" : "FILE",
      "virtual" : false,
      "branchOutType" : "MODIFIED_IN_THEIRS",
      "branchInType" : "APPLIED_THEIRS",
      "latestBranchInType" : "APPLIED_THEIRS",
      "objectIdsMap" : {
        "COMMON_ANCESTOR" : "1548bf81dd7113d48f8ce7759e7f475d3a4a1ae2",
        "OURS" : "1548bf81dd7113d48f8ce7759e7f475d3a4a1ae2",
        "THEIRS" : "e4b40be3564cf95d302a4ad91c65151d3924ec4c",
        "INITIAL_MERGE" : "e4b40be3564cf95d302a4ad91c65151d3924ec4c",
        "LAST_SYNCED_MERGE" : "e4b40be3564cf95d302a4ad91c65151d3924ec4c"
      },
      "component" : "OTHER",
      "conflictedFileParts" : null,
      "conflictsCount" : 0,
      "initialConflictsCount" : 0,
      "description" : null,
      "mergeActionType" : "DEFAULT"
    },
    "src/main/webapp/design-tokens" : {
      "path" : "src/main/webapp/design-tokens",
      "pathType" : "DIR",
      "virtual" : false,
      "branchOutType" : "MODIFIED_IN_THEIRS",
      "branchInType" : "APPLIED_THEIRS",
      "latestBranchInType" : "APPLIED_THEIRS",
      "objectIdsMap" : {
        "COMMON_ANCESTOR" : "c8469bcc20f58ab07817dc730cc74353f625c1e8",
        "OURS" : "c8469bcc20f58ab07817dc730cc74353f625c1e8",
        "THEIRS" : "aacde06408a8efbd97686e05e20ca9a15ce49495",
        "INITIAL_MERGE" : "aacde06408a8efbd97686e05e20ca9a15ce49495",
        "LAST_SYNCED_MERGE" : "aacde06408a8efbd97686e05e20ca9a15ce49495"
      },
      "component" : "OTHER",
      "conflictedFileParts" : null,
      "conflictsCount" : 0,
      "initialConflictsCount" : 0,
      "description" : null,
      "mergeActionType" : "DEFAULT"
    },
    "src/main/webapp/design-tokens/overrides" : {
      "path" : "src/main/webapp/design-tokens/overrides",
      "pathType" : "DIR",
      "virtual" : false,
      "branchOutType" : "MODIFIED_IN_THEIRS",
      "branchInType" : "APPLIED_THEIRS",
      "latestBranchInType" : "APPLIED_THEIRS",
      "objectIdsMap" : {
        "COMMON_ANCESTOR" : "60c31474dbc072ed8b6264d754df0a2d9b2d1cb8",
        "OURS" : "60c31474dbc072ed8b6264d754df0a2d9b2d1cb8",
        "THEIRS" : "4748879428161922e70f2981447878cea7afb382",
        "INITIAL_MERGE" : "4748879428161922e70f2981447878cea7afb382",
        "LAST_SYNCED_MERGE" : "4748879428161922e70f2981447878cea7afb382"
      },
      "component" : "OTHER",
      "conflictedFileParts" : null,
      "conflictsCount" : 0,
      "initialConflictsCount" : 0,
      "description" : null,
      "mergeActionType" : "DEFAULT"
    },
    "src/main/webapp/design-tokens/overrides/components" : {
      "path" : "src/main/webapp/design-tokens/overrides/components",
      "pathType" : "DIR",
      "virtual" : false,
      "branchOutType" : "MODIFIED_IN_THEIRS",
      "branchInType" : "APPLIED_THEIRS",
      "latestBranchInType" : "APPLIED_THEIRS",
      "objectIdsMap" : {
        "COMMON_ANCESTOR" : "0dbd5dc557efd4d829b5eb5b4fce02f633d28e35",
        "OURS" : "0dbd5dc557efd4d829b5eb5b4fce02f633d28e35",
        "THEIRS" : "708ed16c2f3c1a254a37fb5fc0a8657fa486fb02",
        "INITIAL_MERGE" : "708ed16c2f3c1a254a37fb5fc0a8657fa486fb02",
        "LAST_SYNCED_MERGE" : "708ed16c2f3c1a254a37fb5fc0a8657fa486fb02"
      },
      "component" : "OTHER",
      "conflictedFileParts" : null,
      "conflictsCount" : 0,
      "initialConflictsCount" : 0,
      "description" : null,
      "mergeActionType" : "DEFAULT"
    },
    "src/main/webapp/design-tokens/overrides/components/button" : {
      "path" : "src/main/webapp/design-tokens/overrides/components/button",
      "pathType" : "DIR",
      "virtual" : false,
      "branchOutType" : "MODIFIED_IN_THEIRS",
      "branchInType" : "APPLIED_THEIRS",
      "latestBranchInType" : "APPLIED_THEIRS",
      "objectIdsMap" : {
        "COMMON_ANCESTOR" : "8c8b3214a5b76fd73add22ccd157a0d1e1a13c8b",
        "OURS" : "8c8b3214a5b76fd73add22ccd157a0d1e1a13c8b",
        "THEIRS" : "03cb67bd9e11998a9eed2f3f8b15552b762c9770",
        "INITIAL_MERGE" : "03cb67bd9e11998a9eed2f3f8b15552b762c9770",
        "LAST_SYNCED_MERGE" : "03cb67bd9e11998a9eed2f3f8b15552b762c9770"
      },
      "component" : "OTHER",
      "conflictedFileParts" : null,
      "conflictsCount" : 0,
      "initialConflictsCount" : 0,
      "description" : null,
      "mergeActionType" : "DEFAULT"
    },
    "src/main/webapp/design-tokens/overrides/components/button/button.json" : {
      "path" : "src/main/webapp/design-tokens/overrides/components/button/button.json",
      "pathType" : "FILE",
      "virtual" : false,
      "branchOutType" : "MODIFIED_IN_THEIRS",
      "branchInType" : "APPLIED_THEIRS",
      "latestBranchInType" : "APPLIED_THEIRS",
      "objectIdsMap" : {
        "COMMON_ANCESTOR" : "2a6b544bb193e83598b340d22f8790631c21c11d",
        "OURS" : "2a6b544bb193e83598b340d22f8790631c21c11d",
        "THEIRS" : "664d6b30c87a94389aba2ce5d1fa637324de27cc",
        "INITIAL_MERGE" : "664d6b30c87a94389aba2ce5d1fa637324de27cc",
        "LAST_SYNCED_MERGE" : "664d6b30c87a94389aba2ce5d1fa637324de27cc"
      },
      "component" : "OTHER",
      "conflictedFileParts" : null,
      "conflictsCount" : 0,
      "initialConflictsCount" : 0,
      "description" : null,
      "mergeActionType" : "DEFAULT"
    },
    "src/main/webapp/design-tokens/overrides/components/form-controls" : {
      "path" : "src/main/webapp/design-tokens/overrides/components/form-controls",
      "pathType" : "DIR",
      "virtual" : false,
      "branchOutType" : "MODIFIED_IN_THEIRS",
      "branchInType" : "APPLIED_THEIRS",
      "latestBranchInType" : "APPLIED_THEIRS",
      "objectIdsMap" : {
        "COMMON_ANCESTOR" : "7324646eea7e58f69eb35fcd2d5a654205079ec9",
        "OURS" : "7324646eea7e58f69eb35fcd2d5a654205079ec9",
        "THEIRS" : "d762e0b6d8838337ff9f10d32f0285c3bfcf239f",
        "INITIAL_MERGE" : "d762e0b6d8838337ff9f10d32f0285c3bfcf239f",
        "LAST_SYNCED_MERGE" : "d762e0b6d8838337ff9f10d32f0285c3bfcf239f"
      },
      "component" : "OTHER",
      "conflictedFileParts" : null,
      "conflictsCount" : 0,
      "initialConflictsCount" : 0,
      "description" : null,
      "mergeActionType" : "DEFAULT"
    },
    "src/main/webapp/design-tokens/overrides/components/form-controls/form-controls.json" : {
      "path" : "src/main/webapp/design-tokens/overrides/components/form-controls/form-controls.json",
      "pathType" : "FILE",
      "virtual" : false,
      "branchOutType" : "MODIFIED_IN_THEIRS",
      "branchInType" : "APPLIED_THEIRS",
      "latestBranchInType" : "APPLIED_THEIRS",
      "objectIdsMap" : {
        "COMMON_ANCESTOR" : "8a5233f6cba06ff09aa5fa4450dacf765fb165a4",
        "OURS" : "8a5233f6cba06ff09aa5fa4450dacf765fb165a4",
        "THEIRS" : "99a12990b4f766aa8ec9dedb066e30053e0e777a",
        "INITIAL_MERGE" : "99a12990b4f766aa8ec9dedb066e30053e0e777a",
        "LAST_SYNCED_MERGE" : "99a12990b4f766aa8ec9dedb066e30053e0e777a"
      },
      "component" : "OTHER",
      "conflictedFileParts" : null,
      "conflictsCount" : 0,
      "initialConflictsCount" : 0,
      "description" : null,
      "mergeActionType" : "DEFAULT"
    },
    "src/main/webapp/pages" : {
      "path" : "src/main/webapp/pages",
      "pathType" : "DIR",
      "virtual" : false,
      "branchOutType" : "MODIFIED_IN_THEIRS",
      "branchInType" : "APPLIED_THEIRS",
      "latestBranchInType" : "APPLIED_THEIRS",
      "objectIdsMap" : {
        "COMMON_ANCESTOR" : "eaef857ce2237f0b85b08d4c82e6eb70aaa6ade4",
        "OURS" : "eaef857ce2237f0b85b08d4c82e6eb70aaa6ade4",
        "THEIRS" : "447b2b3033eb8c0bc9067a44054c9899283e2db1",
        "INITIAL_MERGE" : "447b2b3033eb8c0bc9067a44054c9899283e2db1",
        "LAST_SYNCED_MERGE" : "447b2b3033eb8c0bc9067a44054c9899283e2db1"
      },
      "component" : "PAGE",
      "conflictedFileParts" : null,
      "conflictsCount" : 0,
      "initialConflictsCount" : 0,
      "description" : null,
      "mergeActionType" : "DEFAULT"
    },
    "src/main/webapp/pages/EmployeeView" : {
      "path" : "src/main/webapp/pages/EmployeeView",
      "pathType" : "DIR",
      "virtual" : false,
      "branchOutType" : "MODIFIED_IN_THEIRS",
      "branchInType" : "APPLIED_THEIRS",
      "latestBranchInType" : "APPLIED_THEIRS",
      "objectIdsMap" : {
        "COMMON_ANCESTOR" : "28a0adc2f0252b4a37b4c6dacd5618fe7f566854",
        "OURS" : "28a0adc2f0252b4a37b4c6dacd5618fe7f566854",
        "THEIRS" : "c712b0a9e2d9d39a3604c8b9aaab432a5a6e1238",
        "INITIAL_MERGE" : "c712b0a9e2d9d39a3604c8b9aaab432a5a6e1238",
        "LAST_SYNCED_MERGE" : "c712b0a9e2d9d39a3604c8b9aaab432a5a6e1238"
      },
      "component" : "PAGE",
      "conflictedFileParts" : null,
      "conflictsCount" : 0,
      "initialConflictsCount" : 0,
      "description" : null,
      "mergeActionType" : "DEFAULT"
    },
    "src/main/webapp/pages/EmployeeView/EmployeeView.css" : {
      "path" : "src/main/webapp/pages/EmployeeView/EmployeeView.css",
      "pathType" : "FILE",
      "virtual" : false,
      "branchOutType" : "MODIFIED_IN_THEIRS",
      "branchInType" : "APPLIED_THEIRS",
      "latestBranchInType" : "APPLIED_THEIRS",
      "objectIdsMap" : {
        "COMMON_ANCESTOR" : "ae4eab7009b99fb0243a7ed47e78007f46617a9e",
        "OURS" : "ae4eab7009b99fb0243a7ed47e78007f46617a9e",
        "THEIRS" : "e1c4b4d9372066b7324ae3a1cbc98457e3cd4204",
        "INITIAL_MERGE" : "e1c4b4d9372066b7324ae3a1cbc98457e3cd4204",
        "LAST_SYNCED_MERGE" : "e1c4b4d9372066b7324ae3a1cbc98457e3cd4204"
      },
      "component" : "PAGE",
      "conflictedFileParts" : null,
      "conflictsCount" : 0,
      "initialConflictsCount" : 0,
      "description" : null,
      "mergeActionType" : "DEFAULT"
    },
    "src/main/webapp/pages/calenderView" : {
      "path" : "src/main/webapp/pages/calenderView",
      "pathType" : "DIR",
      "virtual" : false,
      "branchOutType" : "MODIFIED_IN_THEIRS",
      "branchInType" : "APPLIED_THEIRS",
      "latestBranchInType" : "APPLIED_THEIRS",
      "objectIdsMap" : {
        "COMMON_ANCESTOR" : "60555741a72c98cca563d65f618762bdad2ee65d",
        "OURS" : "60555741a72c98cca563d65f618762bdad2ee65d",
        "THEIRS" : "6d95198fd398f4175f10163ac88651cdbca7e338",
        "INITIAL_MERGE" : "6d95198fd398f4175f10163ac88651cdbca7e338",
        "LAST_SYNCED_MERGE" : "6d95198fd398f4175f10163ac88651cdbca7e338"
      },
      "component" : "PAGE",
      "conflictedFileParts" : null,
      "conflictsCount" : 0,
      "initialConflictsCount" : 0,
      "description" : null,
      "mergeActionType" : "DEFAULT"
    },
    "src/main/webapp/pages/calenderView/calenderView.html" : {
      "path" : "src/main/webapp/pages/calenderView/calenderView.html",
      "pathType" : "FILE",
      "virtual" : false,
      "branchOutType" : "MODIFIED_IN_THEIRS",
      "branchInType" : "APPLIED_THEIRS",
      "latestBranchInType" : "APPLIED_THEIRS",
      "objectIdsMap" : {
        "COMMON_ANCESTOR" : "f647f9ac4d58a189759c645fcae65eff1426d401",
        "OURS" : "f647f9ac4d58a189759c645fcae65eff1426d401",
        "THEIRS" : "16d7d9a165e3611b54913c792d9aa61c04b8344d",
        "INITIAL_MERGE" : "16d7d9a165e3611b54913c792d9aa61c04b8344d",
        "LAST_SYNCED_MERGE" : "16d7d9a165e3611b54913c792d9aa61c04b8344d"
      },
      "component" : "PAGE",
      "conflictedFileParts" : null,
      "conflictsCount" : 0,
      "initialConflictsCount" : 0,
      "description" : null,
      "mergeActionType" : "DEFAULT"
    },
    "src/main/webapp/pages/calenderView/calenderView.js" : {
      "path" : "src/main/webapp/pages/calenderView/calenderView.js",
      "pathType" : "FILE",
      "virtual" : false,
      "branchOutType" : "MODIFIED_IN_THEIRS",
      "branchInType" : "APPLIED_THEIRS",
      "latestBranchInType" : "APPLIED_THEIRS",
      "objectIdsMap" : {
        "COMMON_ANCESTOR" : "c5b2cf8eecc349c4441fcf2886b6f485d1496ae5",
        "OURS" : "c5b2cf8eecc349c4441fcf2886b6f485d1496ae5",
        "THEIRS" : "166a34c70ed312ee3ab061d5ca89c0af6d89a76d",
        "INITIAL_MERGE" : "166a34c70ed312ee3ab061d5ca89c0af6d89a76d",
        "LAST_SYNCED_MERGE" : "166a34c70ed312ee3ab061d5ca89c0af6d89a76d"
      },
      "component" : "PAGE",
      "conflictedFileParts" : null,
      "conflictsCount" : 0,
      "initialConflictsCount" : 0,
      "description" : null,
      "mergeActionType" : "DEFAULT"
    },
    "src/main/webapp/pages/emppreferencesday" : {
      "path" : "src/main/webapp/pages/emppreferencesday",
      "pathType" : "DIR",
      "virtual" : false,
      "branchOutType" : "MODIFIED_IN_THEIRS",
      "branchInType" : "APPLIED_THEIRS",
      "latestBranchInType" : "APPLIED_THEIRS",
      "objectIdsMap" : {
        "COMMON_ANCESTOR" : "2fcc1f1bc15c3bba2b26ef59f13bb122c078e18e",
        "OURS" : "2fcc1f1bc15c3bba2b26ef59f13bb122c078e18e",
        "THEIRS" : "62caf24a3b18c99c4c560016911a411d428bd266",
        "INITIAL_MERGE" : "62caf24a3b18c99c4c560016911a411d428bd266",
        "LAST_SYNCED_MERGE" : "62caf24a3b18c99c4c560016911a411d428bd266"
      },
      "component" : "PAGE",
      "conflictedFileParts" : null,
      "conflictsCount" : 0,
      "initialConflictsCount" : 0,
      "description" : null,
      "mergeActionType" : "DEFAULT"
    },
    "src/main/webapp/pages/emppreferencesday/emppreferencesday.js" : {
      "path" : "src/main/webapp/pages/emppreferencesday/emppreferencesday.js",
      "pathType" : "FILE",
      "virtual" : false,
      "branchOutType" : "MODIFIED_IN_THEIRS",
      "branchInType" : "APPLIED_THEIRS",
      "latestBranchInType" : "APPLIED_THEIRS",
      "objectIdsMap" : {
        "COMMON_ANCESTOR" : "9035de9e4edfbd6b917a3fabadaab14d2b6345f6",
        "OURS" : "9035de9e4edfbd6b917a3fabadaab14d2b6345f6",
        "THEIRS" : "495951417fd539c656948ac5c04c249fb5a5b9c9",
        "INITIAL_MERGE" : "495951417fd539c656948ac5c04c249fb5a5b9c9",
        "LAST_SYNCED_MERGE" : "495951417fd539c656948ac5c04c249fb5a5b9c9"
      },
      "component" : "PAGE",
      "conflictedFileParts" : null,
      "conflictsCount" : 0,
      "initialConflictsCount" : 0,
      "description" : null,
      "mergeActionType" : "DEFAULT"
    },
    "src/main/webapp/pages/emppreferencesrepeat" : {
      "path" : "src/main/webapp/pages/emppreferencesrepeat",
      "pathType" : "DIR",
      "virtual" : false,
      "branchOutType" : "MODIFIED_IN_THEIRS",
      "branchInType" : "APPLIED_THEIRS",
      "latestBranchInType" : "APPLIED_THEIRS",
      "objectIdsMap" : {
        "COMMON_ANCESTOR" : "b664a3d501d63bd7c93c4652e6867dbbae612ec8",
        "OURS" : "b664a3d501d63bd7c93c4652e6867dbbae612ec8",
        "THEIRS" : "9f4f0f51209ce3de14bdb0076eb0410d7d16113e",
        "INITIAL_MERGE" : "9f4f0f51209ce3de14bdb0076eb0410d7d16113e",
        "LAST_SYNCED_MERGE" : "9f4f0f51209ce3de14bdb0076eb0410d7d16113e"
      },
      "component" : "PAGE",
      "conflictedFileParts" : null,
      "conflictsCount" : 0,
      "initialConflictsCount" : 0,
      "description" : null,
      "mergeActionType" : "DEFAULT"
    },
    "src/main/webapp/pages/emppreferencesrepeat/emppreferencesrepeat.js" : {
      "path" : "src/main/webapp/pages/emppreferencesrepeat/emppreferencesrepeat.js",
      "pathType" : "FILE",
      "virtual" : false,
      "branchOutType" : "MODIFIED_IN_THEIRS",
      "branchInType" : "APPLIED_THEIRS",
      "latestBranchInType" : "APPLIED_THEIRS",
      "objectIdsMap" : {
        "COMMON_ANCESTOR" : "06b064c32aab68d03b8be1c94778695b90805ada",
        "OURS" : "06b064c32aab68d03b8be1c94778695b90805ada",
        "THEIRS" : "804fb831abf5f8ff61fb867a90f489efc2775a04",
        "INITIAL_MERGE" : "804fb831abf5f8ff61fb867a90f489efc2775a04",
        "LAST_SYNCED_MERGE" : "804fb831abf5f8ff61fb867a90f489efc2775a04"
      },
      "component" : "PAGE",
      "conflictedFileParts" : null,
      "conflictsCount" : 0,
      "initialConflictsCount" : 0,
      "description" : null,
      "mergeActionType" : "DEFAULT"
    },
    "src/main/webapp/pages/mgrschedulecfgmonth" : {
      "path" : "src/main/webapp/pages/mgrschedulecfgmonth",
      "pathType" : "DIR",
      "virtual" : false,
      "branchOutType" : "MODIFIED_IN_THEIRS",
      "branchInType" : "APPLIED_THEIRS",
      "latestBranchInType" : "APPLIED_THEIRS",
      "objectIdsMap" : {
        "COMMON_ANCESTOR" : "f5745b92203cac0fa1eeb524b87c93765a680dad",
        "OURS" : "f5745b92203cac0fa1eeb524b87c93765a680dad",
        "THEIRS" : "fa915878681643b985bb6b9486c3d8e7a2536bfb",
        "INITIAL_MERGE" : "fa915878681643b985bb6b9486c3d8e7a2536bfb",
        "LAST_SYNCED_MERGE" : "fa915878681643b985bb6b9486c3d8e7a2536bfb"
      },
      "component" : "PAGE",
      "conflictedFileParts" : null,
      "conflictsCount" : 0,
      "initialConflictsCount" : 0,
      "description" : null,
      "mergeActionType" : "DEFAULT"
    },
    "src/main/webapp/pages/mgrschedulecfgmonth/mgrschedulecfgmonth.js" : {
      "path" : "src/main/webapp/pages/mgrschedulecfgmonth/mgrschedulecfgmonth.js",
      "pathType" : "FILE",
      "virtual" : false,
      "branchOutType" : "MODIFIED_IN_THEIRS",
      "branchInType" : "APPLIED_THEIRS",
      "latestBranchInType" : "APPLIED_THEIRS",
      "objectIdsMap" : {
        "COMMON_ANCESTOR" : "283873de2a03974df9ed652c722ffbbec4391bd6",
        "OURS" : "283873de2a03974df9ed652c722ffbbec4391bd6",
        "THEIRS" : "1ef144e3ab0ef00ea972236be050d75795878c4d",
        "INITIAL_MERGE" : "1ef144e3ab0ef00ea972236be050d75795878c4d",
        "LAST_SYNCED_MERGE" : "1ef144e3ab0ef00ea972236be050d75795878c4d"
      },
      "component" : "PAGE",
      "conflictedFileParts" : null,
      "conflictsCount" : 0,
      "initialConflictsCount" : 0,
      "description" : null,
      "mergeActionType" : "DEFAULT"
    },
    "src/main/webapp/pages/pages-config.json" : {
      "path" : "src/main/webapp/pages/pages-config.json",
      "pathType" : "FILE",
      "virtual" : false,
      "branchOutType" : "MODIFIED_IN_THEIRS",
      "branchInType" : "APPLIED_THEIRS",
      "latestBranchInType" : "APPLIED_THEIRS",
      "objectIdsMap" : {
        "COMMON_ANCESTOR" : "94fca3e77bc11de483065b3d7cdbfe4ae7b9272b",
        "OURS" : "94fca3e77bc11de483065b3d7cdbfe4ae7b9272b",
        "THEIRS" : "fab60a51218661f6382165da86cc111ee0f9be5f",
        "INITIAL_MERGE" : "fab60a51218661f6382165da86cc111ee0f9be5f",
        "LAST_SYNCED_MERGE" : "fab60a51218661f6382165da86cc111ee0f9be5f"
      },
      "component" : "PAGE",
      "conflictedFileParts" : null,
      "conflictsCount" : 0,
      "initialConflictsCount" : 0,
      "description" : null,
      "mergeActionType" : "DEFAULT"
    },
    "src/main/webapp/pages/scheduleTopNav" : {
      "path" : "src/main/webapp/pages/scheduleTopNav",
      "pathType" : "DIR",
      "virtual" : false,
      "branchOutType" : "MODIFIED_IN_THEIRS",
      "branchInType" : "APPLIED_THEIRS",
      "latestBranchInType" : "APPLIED_THEIRS",
      "objectIdsMap" : {
        "COMMON_ANCESTOR" : "67c8d9cf3e5d7845942d35c6d7c71f84e035b0ea",
        "OURS" : "67c8d9cf3e5d7845942d35c6d7c71f84e035b0ea",
        "THEIRS" : "76daf99b443d87a91550b7b80031a9f14a246ed1",
        "INITIAL_MERGE" : "76daf99b443d87a91550b7b80031a9f14a246ed1",
        "LAST_SYNCED_MERGE" : "76daf99b443d87a91550b7b80031a9f14a246ed1"
      },
      "component" : "PAGE",
      "conflictedFileParts" : null,
      "conflictsCount" : 0,
      "initialConflictsCount" : 0,
      "description" : null,
      "mergeActionType" : "DEFAULT"
    },
    "src/main/webapp/pages/scheduleTopNav/scheduleTopNav.css" : {
      "path" : "src/main/webapp/pages/scheduleTopNav/scheduleTopNav.css",
      "pathType" : "FILE",
      "virtual" : false,
      "branchOutType" : "MODIFIED_IN_THEIRS",
      "branchInType" : "APPLIED_THEIRS",
      "latestBranchInType" : "APPLIED_THEIRS",
      "objectIdsMap" : {
        "COMMON_ANCESTOR" : "4aa93e330d2fae4a7bdedb80f0e563a859e76a16",
        "OURS" : "4aa93e330d2fae4a7bdedb80f0e563a859e76a16",
        "THEIRS" : "7f3e4922be73b382e749c11cae66779b985f1d45",
        "INITIAL_MERGE" : "7f3e4922be73b382e749c11cae66779b985f1d45",
        "LAST_SYNCED_MERGE" : "7f3e4922be73b382e749c11cae66779b985f1d45"
      },
      "component" : "PAGE",
      "conflictedFileParts" : null,
      "conflictsCount" : 0,
      "initialConflictsCount" : 0,
      "description" : null,
      "mergeActionType" : "DEFAULT"
    },
    "src/main/webapp/pages/scheduleTopNav/scheduleTopNav.html" : {
      "path" : "src/main/webapp/pages/scheduleTopNav/scheduleTopNav.html",
      "pathType" : "FILE",
      "virtual" : false,
      "branchOutType" : "MODIFIED_IN_THEIRS",
      "branchInType" : "APPLIED_THEIRS",
      "latestBranchInType" : "APPLIED_THEIRS",
      "objectIdsMap" : {
        "COMMON_ANCESTOR" : "cea14671241ee729e9802a1570339dcdd2ffabbc",
        "OURS" : "cea14671241ee729e9802a1570339dcdd2ffabbc",
        "THEIRS" : "dbbb26f978ebe40174029fed5372fb4084430a19",
        "INITIAL_MERGE" : "dbbb26f978ebe40174029fed5372fb4084430a19",
        "LAST_SYNCED_MERGE" : "dbbb26f978ebe40174029fed5372fb4084430a19"
      },
      "component" : "PAGE",
      "conflictedFileParts" : null,
      "conflictsCount" : 0,
      "initialConflictsCount" : 0,
      "description" : null,
      "mergeActionType" : "DEFAULT"
    },
    "src/main/webapp/pages/topnav" : {
      "path" : "src/main/webapp/pages/topnav",
      "pathType" : "DIR",
      "virtual" : false,
      "branchOutType" : "MODIFIED_IN_THEIRS",
      "branchInType" : "APPLIED_THEIRS",
      "latestBranchInType" : "APPLIED_THEIRS",
      "objectIdsMap" : {
        "COMMON_ANCESTOR" : "a6fc672cee5f396d1fd332c7501b69126f68e876",
        "OURS" : "a6fc672cee5f396d1fd332c7501b69126f68e876",
        "THEIRS" : "07b0658600918a90507145ec0a6e7f9710d086ca",
        "INITIAL_MERGE" : "07b0658600918a90507145ec0a6e7f9710d086ca",
        "LAST_SYNCED_MERGE" : "07b0658600918a90507145ec0a6e7f9710d086ca"
      },
      "component" : "PAGE",
      "conflictedFileParts" : null,
      "conflictsCount" : 0,
      "initialConflictsCount" : 0,
      "description" : null,
      "mergeActionType" : "DEFAULT"
    },
    "src/main/webapp/pages/topnav/topnav.css" : {
      "path" : "src/main/webapp/pages/topnav/topnav.css",
      "pathType" : "FILE",
      "virtual" : false,
      "branchOutType" : "MODIFIED_IN_THEIRS",
      "branchInType" : "APPLIED_THEIRS",
      "latestBranchInType" : "APPLIED_THEIRS",
      "objectIdsMap" : {
        "COMMON_ANCESTOR" : "3dad93b8fe67a376aa2c2f92de8d344b5cd28bf4",
        "OURS" : "3dad93b8fe67a376aa2c2f92de8d344b5cd28bf4",
        "THEIRS" : "da1a8debe5f9602e5070603195629c223ea11dfb",
        "INITIAL_MERGE" : "da1a8debe5f9602e5070603195629c223ea11dfb",
        "LAST_SYNCED_MERGE" : "da1a8debe5f9602e5070603195629c223ea11dfb"
      },
      "component" : "PAGE",
      "conflictedFileParts" : null,
      "conflictsCount" : 0,
      "initialConflictsCount" : 0,
      "description" : null,
      "mergeActionType" : "DEFAULT"
    }
  }
}
